<?xml version="1.0" encoding="utf-8"?>
<LanguageData>

  <!-- Grimoires -->

  <!--<TM_Book_Pools.rulePack.rulesStrings.0>subject_bookType->魔法书</TM_Book_Pools.rulePack.rulesStrings.0>-->
  <!--<TM_Book_Pools.rulePack.rulesStrings.1>subject_bookType->对此</TM_Book_Pools.rulePack.rulesStrings.1>-->
  <!--<TM_Book_Pools.rulePack.rulesStrings.2>subject_bookType->法典</TM_Book_Pools.rulePack.rulesStrings.2>-->
  <!--<TM_Book_Pools.rulePack.rulesStrings.3>subject_bookType->选集</TM_Book_Pools.rulePack.rulesStrings.3>-->
  <!--<TM_Book_Pools.rulePack.rulesStrings.4>subject_bookType->书卷</TM_Book_Pools.rulePack.rulesStrings.4>-->
  <!--<TM_Book_Pools.rulePack.rulesStrings.5>subject_bookType->编年史</TM_Book_Pools.rulePack.rulesStrings.5>-->
  <!--<TM_Book_Pools.rulePack.rulesStrings.6>subject_bookType->指南</TM_Book_Pools.rulePack.rulesStrings.6>-->
  <!--<TM_Book_Pools.rulePack.rulesStrings.7>subject_teachingType->法典</TM_Book_Pools.rulePack.rulesStrings.7>-->
  <!--<TM_Book_Pools.rulePack.rulesStrings.8>subject_teachingType->插图</TM_Book_Pools.rulePack.rulesStrings.8>-->
  <!--<TM_Book_Pools.rulePack.rulesStrings.9>subject_teachingType->集合</TM_Book_Pools.rulePack.rulesStrings.9>-->
  <!--<TM_Book_Pools.rulePack.rulesStrings.10>subject_teachingType->捆</TM_Book_Pools.rulePack.rulesStrings.10>-->
  <!--<TM_Book_Pools.rulePack.rulesStrings.11>subject_teachingType->编年史</TM_Book_Pools.rulePack.rulesStrings.11>-->
  <!--<TM_Book_Pools.rulePack.rulesStrings.12>subject_teachingType->指南</TM_Book_Pools.rulePack.rulesStrings.12>-->
  <!--<TM_Book_Pools.rulePack.rulesStrings.13>subject_teachingType->技术</TM_Book_Pools.rulePack.rulesStrings.13>-->
  <!--<TM_Book_Pools.rulePack.rulesStrings.14>TM_randNoun_Magic->死亡</TM_Book_Pools.rulePack.rulesStrings.14>-->
  <!--<TM_Book_Pools.rulePack.rulesStrings.15>TM_randNoun_Magic->生活</TM_Book_Pools.rulePack.rulesStrings.15>-->
  <!--<TM_Book_Pools.rulePack.rulesStrings.16>TM_randNoun_Magic->爱</TM_Book_Pools.rulePack.rulesStrings.16>-->
  <!--<TM_Book_Pools.rulePack.rulesStrings.17>TM_randNoun_Magic->智慧</TM_Book_Pools.rulePack.rulesStrings.17>-->
  <!--<TM_Book_Pools.rulePack.rulesStrings.18>TM_randNoun_Magic->拼写</TM_Book_Pools.rulePack.rulesStrings.18>-->
  <!--<TM_Book_Pools.rulePack.rulesStrings.19>TM_randNoun_Magic->魅力</TM_Book_Pools.rulePack.rulesStrings.19>-->
  <!--<TM_Book_Pools.rulePack.rulesStrings.20>TM_randNoun_Magic->药水</TM_Book_Pools.rulePack.rulesStrings.20>-->
  <!--<TM_Book_Pools.rulePack.rulesStrings.21>TM_randNoun_Magic->魔杖</TM_Book_Pools.rulePack.rulesStrings.21>-->
  <!--<TM_Book_Pools.rulePack.rulesStrings.22>TM_randNoun_Magic->咒语</TM_Book_Pools.rulePack.rulesStrings.22>-->
  <!--<TM_Book_Pools.rulePack.rulesStrings.23>TM_randNoun_Magic->仪式</TM_Book_Pools.rulePack.rulesStrings.23>-->
  <!--<TM_Book_Pools.rulePack.rulesStrings.24>TM_randNoun_Magic->炼金术</TM_Book_Pools.rulePack.rulesStrings.24>-->
  <!--<TM_Book_Pools.rulePack.rulesStrings.25>TM_randNoun_Magic->巫术</TM_Book_Pools.rulePack.rulesStrings.25>-->
  <!--<TM_Book_Pools.rulePack.rulesStrings.26>TM_randNoun_Magic->向导</TM_Book_Pools.rulePack.rulesStrings.26>-->
  <!--<TM_Book_Pools.rulePack.rulesStrings.27>TM_randNoun_Magic->女巫</TM_Book_Pools.rulePack.rulesStrings.27>-->
  <!--<TM_Book_Pools.rulePack.rulesStrings.28>TM_randNoun_Magic->女巫</TM_Book_Pools.rulePack.rulesStrings.28>-->
  <!--<TM_Book_Pools.rulePack.rulesStrings.29>TM_randNoun_Magic->神秘</TM_Book_Pools.rulePack.rulesStrings.29>-->
  <!--<TM_Book_Pools.rulePack.rulesStrings.30>TM_randNoun_Magic->召唤</TM_Book_Pools.rulePack.rulesStrings.30>-->
  <!--<TM_Book_Pools.rulePack.rulesStrings.31>TM_randNoun_Magic->护身符</TM_Book_Pools.rulePack.rulesStrings.31>-->
  <!--<TM_Book_Pools.rulePack.rulesStrings.32>TM_randNoun_Magic->护身符</TM_Book_Pools.rulePack.rulesStrings.32>-->
  <!--<TM_Book_Pools.rulePack.rulesStrings.33>TM_randNoun_Magic->印记</TM_Book_Pools.rulePack.rulesStrings.33>-->
  <!--<TM_Book_Pools.rulePack.rulesStrings.34>TM_randNoun_Magic->魔法书</TM_Book_Pools.rulePack.rulesStrings.34>-->
  <!--<TM_Book_Pools.rulePack.rulesStrings.35>TM_randNoun_Magic->阿卡纳</TM_Book_Pools.rulePack.rulesStrings.35>-->
  <!--<TM_Book_Pools.rulePack.rulesStrings.36>TM_randNoun_Magic->召唤</TM_Book_Pools.rulePack.rulesStrings.36>-->
  <!--<TM_Book_Pools.rulePack.rulesStrings.37>TM_randNoun_Magic->十六进制</TM_Book_Pools.rulePack.rulesStrings.37>-->
  <!--<TM_Book_Pools.rulePack.rulesStrings.38>TM_randNoun_Magic->诅咒</TM_Book_Pools.rulePack.rulesStrings.38>-->
  <!--<TM_Book_Pools.rulePack.rulesStrings.39>TM_randNoun_Magic->占卜</TM_Book_Pools.rulePack.rulesStrings.39>-->
  <!--<TM_Book_Pools.rulePack.rulesStrings.40>TM_randNoun_Magic->死灵</TM_Book_Pools.rulePack.rulesStrings.40>-->
  <!--<TM_Book_Pools.rulePack.rulesStrings.41>TM_randNoun_Magic->法术书</TM_Book_Pools.rulePack.rulesStrings.41>-->
  <!--<TM_Book_Pools.rulePack.rulesStrings.42>TM_randNoun_Magic->熟悉</TM_Book_Pools.rulePack.rulesStrings.42>-->
  <!--<TM_Book_Pools.rulePack.rulesStrings.43>TM_randNoun_Magic->灵丹妙药</TM_Book_Pools.rulePack.rulesStrings.43>-->
  <!--<TM_Book_Pools.rulePack.rulesStrings.44>TM_randNoun_Magic->集会</TM_Book_Pools.rulePack.rulesStrings.44>-->
  <!--<TM_Book_Pools.rulePack.rulesStrings.45>TM_randNoun_Magic->甲骨文</TM_Book_Pools.rulePack.rulesStrings.45>-->
  <!--<TM_Book_Pools.rulePack.rulesStrings.46>TM_randNoun_Magic->先知</TM_Book_Pools.rulePack.rulesStrings.46>-->
  <!--<TM_Book_Pools.rulePack.rulesStrings.47>TM_randNoun_Magic->符文</TM_Book_Pools.rulePack.rulesStrings.47>-->
  <!--<TM_Book_Pools.rulePack.rulesStrings.48>subject_Magic->死亡</TM_Book_Pools.rulePack.rulesStrings.48>-->
  <!--<TM_Book_Pools.rulePack.rulesStrings.49>subject_Magic->生活</TM_Book_Pools.rulePack.rulesStrings.49>-->
  <!--<TM_Book_Pools.rulePack.rulesStrings.50>subject_Magic->电源</TM_Book_Pools.rulePack.rulesStrings.50>-->
  <!--<TM_Book_Pools.rulePack.rulesStrings.51>subject_Magic->火</TM_Book_Pools.rulePack.rulesStrings.51>-->
  <!--<TM_Book_Pools.rulePack.rulesStrings.52>subject_Magic->冰</TM_Book_Pools.rulePack.rulesStrings.52>-->
  <!--<TM_Book_Pools.rulePack.rulesStrings.53>subject_Magic->闪电</TM_Book_Pools.rulePack.rulesStrings.53>-->
  <!--<TM_Book_Pools.rulePack.rulesStrings.54>subject_Magic->电源</TM_Book_Pools.rulePack.rulesStrings.54>-->
  <!--<TM_Book_Pools.rulePack.rulesStrings.55>subject_Magic->奥术</TM_Book_Pools.rulePack.rulesStrings.55>-->
  <!--<TM_Book_Pools.rulePack.rulesStrings.56>subject_Magic->魔法</TM_Book_Pools.rulePack.rulesStrings.56>-->
  <!--<TM_Book_Pools.rulePack.rulesStrings.57>subject_Magic->风</TM_Book_Pools.rulePack.rulesStrings.57>-->
  <!--<TM_Book_Pools.rulePack.rulesStrings.58>subject_Magic->地球</TM_Book_Pools.rulePack.rulesStrings.58>-->
  <!--<TM_Book_Pools.rulePack.rulesStrings.59>subject_Magic->水</TM_Book_Pools.rulePack.rulesStrings.59>-->
  <!--<TM_Book_Pools.rulePack.rulesStrings.60>subject_Magic->精神</TM_Book_Pools.rulePack.rulesStrings.60>-->
  <!--<TM_Book_Pools.rulePack.rulesStrings.61>subject_Magic->黑暗</TM_Book_Pools.rulePack.rulesStrings.61>-->
  <!--<TM_Book_Pools.rulePack.rulesStrings.62>subject_Magic->轻</TM_Book_Pools.rulePack.rulesStrings.62>-->
  <!--<TM_Book_Pools.rulePack.rulesStrings.63>subject_Magic->时间</TM_Book_Pools.rulePack.rulesStrings.63>-->
  <!--<TM_Book_Pools.rulePack.rulesStrings.64>subject_Magic->幻象</TM_Book_Pools.rulePack.rulesStrings.64>-->
  <!--<TM_Book_Pools.rulePack.rulesStrings.65>subject_Magic->治疗</TM_Book_Pools.rulePack.rulesStrings.65>-->
  <!--<TM_Book_Pools.rulePack.rulesStrings.66>subject_Magic->转换</TM_Book_Pools.rulePack.rulesStrings.66>-->
  <!--<TM_Book_Pools.rulePack.rulesStrings.67>subject_Magic->召唤</TM_Book_Pools.rulePack.rulesStrings.67>-->
  <!--<TM_Book_Pools.rulePack.rulesStrings.68>subject_Magic->炼金术</TM_Book_Pools.rulePack.rulesStrings.68>-->
  <!--<TM_Book_Pools.rulePack.rulesStrings.69>subject_Magic->死灵术</TM_Book_Pools.rulePack.rulesStrings.69>-->
  <!--<TM_Book_Pools.rulePack.rulesStrings.70>subject_Magic->结界</TM_Book_Pools.rulePack.rulesStrings.70>-->
  <!--<TM_Book_Pools.rulePack.rulesStrings.71>subject_Magic->符文</TM_Book_Pools.rulePack.rulesStrings.71>-->
  <!--<TM_Book_Pools.rulePack.rulesStrings.72>subject_Magic->占卜</TM_Book_Pools.rulePack.rulesStrings.72>-->
  <!--<TM_Book_Pools.rulePack.rulesStrings.73>subject_Magic->神秘主义</TM_Book_Pools.rulePack.rulesStrings.73>-->
  <!--<TM_Book_Pools.rulePack.rulesStrings.74>subject_Magic->星体投射</TM_Book_Pools.rulePack.rulesStrings.74>-->
  <!--<TM_Book_Pools.rulePack.rulesStrings.75>subject_Magic->心灵传动</TM_Book_Pools.rulePack.rulesStrings.75>-->
  <!--<TM_Book_Pools.rulePack.rulesStrings.76>subject_Magic->心灵感应</TM_Book_Pools.rulePack.rulesStrings.76>-->
  <!--<TM_Book_Pools.rulePack.rulesStrings.77>subject_Magic->变形</TM_Book_Pools.rulePack.rulesStrings.77>-->
  <!--<TM_Book_Pools.rulePack.rulesStrings.78>subject_Magic->元素</TM_Book_Pools.rulePack.rulesStrings.78>-->
  <!--<TM_Book_Pools.rulePack.rulesStrings.79>subject_Magic->门户</TM_Book_Pools.rulePack.rulesStrings.79>-->
  <!--<TM_Book_Pools.rulePack.rulesStrings.80>subject_Magic->梦游</TM_Book_Pools.rulePack.rulesStrings.80>-->
  <!--<TM_Book_Pools.rulePack.rulesStrings.81>subject_Magic->印记</TM_Book_Pools.rulePack.rulesStrings.81>-->
  <!--<TM_Book_Pools.rulePack.rulesStrings.82>subject_Magic->家族</TM_Book_Pools.rulePack.rulesStrings.82>-->
  <!--<TM_Book_Pools.rulePack.rulesStrings.83>subject_Magic->十六进制</TM_Book_Pools.rulePack.rulesStrings.83>-->
  <!--<TM_Book_Pools.rulePack.rulesStrings.84>subject_Magic->诅咒</TM_Book_Pools.rulePack.rulesStrings.84>-->
  <!--<TM_Book_Pools.rulePack.rulesStrings.85>subject_Magic->药水</TM_Book_Pools.rulePack.rulesStrings.85>-->
  <!--<TM_Book_Pools.rulePack.rulesStrings.86>subject_Magic->魅力</TM_Book_Pools.rulePack.rulesStrings.86>-->
  <!--<TM_Book_Pools.rulePack.rulesStrings.87>TM_randAdjective_Magic->古老的</TM_Book_Pools.rulePack.rulesStrings.87>-->
  <!--<TM_Book_Pools.rulePack.rulesStrings.88>TM_randAdjective_Magic->神奇</TM_Book_Pools.rulePack.rulesStrings.88>-->
  <!--<TM_Book_Pools.rulePack.rulesStrings.89>TM_randAdjective_Magic->灵感</TM_Book_Pools.rulePack.rulesStrings.89>-->
  <!--<TM_Book_Pools.rulePack.rulesStrings.90>TM_randAdjective_Magic->热情</TM_Book_Pools.rulePack.rulesStrings.90>-->
  <!--<TM_Book_Pools.rulePack.rulesStrings.91>TM_randAdjective_Magic->邪恶</TM_Book_Pools.rulePack.rulesStrings.91>-->
  <!--<TM_Book_Pools.rulePack.rulesStrings.92>TM_randAdjective_Magic->混沌</TM_Book_Pools.rulePack.rulesStrings.92>-->
  <!--<TM_Book_Pools.rulePack.rulesStrings.93>TM_randAdjective_Magic->神秘</TM_Book_Pools.rulePack.rulesStrings.93>-->
  <!--<TM_Book_Pools.rulePack.rulesStrings.94>TM_randAdjective_Magic->神秘</TM_Book_Pools.rulePack.rulesStrings.94>-->
  <!--<TM_Book_Pools.rulePack.rulesStrings.95>TM_randAdjective_Magic->奥术</TM_Book_Pools.rulePack.rulesStrings.95>-->
  <!--<TM_Book_Pools.rulePack.rulesStrings.96>TM_randAdjective_Magic->强大</TM_Book_Pools.rulePack.rulesStrings.96>-->
  <!--<TM_Book_Pools.rulePack.rulesStrings.97>TM_randAdjective_Magic->虚幻</TM_Book_Pools.rulePack.rulesStrings.97>-->
  <!--<TM_Book_Pools.rulePack.rulesStrings.98>TM_randAdjective_Magic->禁止</TM_Book_Pools.rulePack.rulesStrings.98>-->
  <!--<TM_Book_Pools.rulePack.rulesStrings.99>TM_randAdjective_Magic->复杂</TM_Book_Pools.rulePack.rulesStrings.99>-->
  <!--<TM_Book_Pools.rulePack.rulesStrings.100>TM_randAdjective_Magic->深奥</TM_Book_Pools.rulePack.rulesStrings.100>-->
  <!--<TM_Book_Pools.rulePack.rulesStrings.101>TM_randAdjective_Magic->神圣</TM_Book_Pools.rulePack.rulesStrings.101>-->
  <!--<TM_Book_Pools.rulePack.rulesStrings.102>TM_randAdjective_Magic->光谱</TM_Book_Pools.rulePack.rulesStrings.102>-->
  <!--<TM_Book_Pools.rulePack.rulesStrings.103>TM_randTheme_Magic->知识</TM_Book_Pools.rulePack.rulesStrings.103>-->
  <!--<TM_Book_Pools.rulePack.rulesStrings.104>TM_randTheme_Magic->了解</TM_Book_Pools.rulePack.rulesStrings.104>-->
  <!--<TM_Book_Pools.rulePack.rulesStrings.105>TM_randTheme_Magic->电源</TM_Book_Pools.rulePack.rulesStrings.105>-->
  <!--<TM_Book_Pools.rulePack.rulesStrings.106>TM_randTheme_Magic->转换</TM_Book_Pools.rulePack.rulesStrings.106>-->
  <!--<TM_Book_Pools.rulePack.rulesStrings.107>TM_randTheme_Magic->神秘</TM_Book_Pools.rulePack.rulesStrings.107>-->
  <!--<TM_Book_Pools.rulePack.rulesStrings.108>TM_randTheme_Magic->启蒙</TM_Book_Pools.rulePack.rulesStrings.108>-->
  <!--<TM_Book_Pools.rulePack.rulesStrings.109>TM_randTheme_Magic->余额</TM_Book_Pools.rulePack.rulesStrings.109>-->
  <!--<TM_Book_Pools.rulePack.rulesStrings.110>TM_randTheme_Magic->保护</TM_Book_Pools.rulePack.rulesStrings.110>-->
  <!--<TM_Book_Pools.rulePack.rulesStrings.111>TM_randTheme_Magic->治疗</TM_Book_Pools.rulePack.rulesStrings.111>-->
  <!--<TM_Book_Pools.rulePack.rulesStrings.112>TM_randTheme_Magic->智慧</TM_Book_Pools.rulePack.rulesStrings.112>-->
  <!--<TM_Book_Pools.rulePack.rulesStrings.113>TM_randTheme_Magic->发现</TM_Book_Pools.rulePack.rulesStrings.113>-->
  <!--<TM_Book_Pools.rulePack.rulesStrings.114>TM_randTheme_Magic->创建</TM_Book_Pools.rulePack.rulesStrings.114>-->
  <!--<TM_Book_Pools.rulePack.rulesStrings.115>TM_randTheme_Magic->旧版</TM_Book_Pools.rulePack.rulesStrings.115>-->
  <!--<TM_Book_Pools.rulePack.rulesStrings.116>TM_randTheme_Magic->炼金术</TM_Book_Pools.rulePack.rulesStrings.116>-->
  <!--<TM_Book_Pools.rulePack.rulesStrings.117>TM_randTheme_Magic->命运</TM_Book_Pools.rulePack.rulesStrings.117>-->
  <!--<TM_Book_Pools.rulePack.rulesStrings.118>TM_randTheme_Magic->和谐</TM_Book_Pools.rulePack.rulesStrings.118>-->
  <!--<TM_Book_Pools.rulePack.rulesStrings.119>TM_randTheme_Magic->自然</TM_Book_Pools.rulePack.rulesStrings.119>-->
  <!--<TM_Book_Pools.rulePack.rulesStrings.120>TM_randNoun_Might->战斗</TM_Book_Pools.rulePack.rulesStrings.120>-->
  <!--<TM_Book_Pools.rulePack.rulesStrings.121>TM_randNoun_Might->战争</TM_Book_Pools.rulePack.rulesStrings.121>-->
  <!--<TM_Book_Pools.rulePack.rulesStrings.122>TM_randNoun_Might->战斗</TM_Book_Pools.rulePack.rulesStrings.122>-->
  <!--<TM_Book_Pools.rulePack.rulesStrings.123>TM_randNoun_Might->奋斗</TM_Book_Pools.rulePack.rulesStrings.123>-->
  <!--<TM_Book_Pools.rulePack.rulesStrings.124>TM_randNoun_Might->冲突</TM_Book_Pools.rulePack.rulesStrings.124>-->
  <!--<TM_Book_Pools.rulePack.rulesStrings.125>TM_randNoun_Might->征服</TM_Book_Pools.rulePack.rulesStrings.125>-->
  <!--<TM_Book_Pools.rulePack.rulesStrings.126>TM_randNoun_Might->胜利</TM_Book_Pools.rulePack.rulesStrings.126>-->
  <!--<TM_Book_Pools.rulePack.rulesStrings.127>TM_randNoun_Might->胜利</TM_Book_Pools.rulePack.rulesStrings.127>-->
  <!--<TM_Book_Pools.rulePack.rulesStrings.128>TM_randNoun_Might->荣耀</TM_Book_Pools.rulePack.rulesStrings.128>-->
  <!--<TM_Book_Pools.rulePack.rulesStrings.129>TM_randNoun_Might->价值</TM_Book_Pools.rulePack.rulesStrings.129>-->
  <!--<TM_Book_Pools.rulePack.rulesStrings.130>TM_randNoun_Might->英雄主义</TM_Book_Pools.rulePack.rulesStrings.130>-->
  <!--<TM_Book_Pools.rulePack.rulesStrings.131>TM_randNoun_Might->武器</TM_Book_Pools.rulePack.rulesStrings.131>-->
  <!--<TM_Book_Pools.rulePack.rulesStrings.132>TM_randNoun_Might->屏蔽</TM_Book_Pools.rulePack.rulesStrings.132>-->
  <!--<TM_Book_Pools.rulePack.rulesStrings.133>TM_randNoun_Might->装甲</TM_Book_Pools.rulePack.rulesStrings.133>-->
  <!--<TM_Book_Pools.rulePack.rulesStrings.134>TM_randNoun_Might->剑</TM_Book_Pools.rulePack.rulesStrings.134>-->
  <!--<TM_Book_Pools.rulePack.rulesStrings.135>TM_randNoun_Might->斧头</TM_Book_Pools.rulePack.rulesStrings.135>-->
  <!--<TM_Book_Pools.rulePack.rulesStrings.136>TM_randNoun_Might->矛</TM_Book_Pools.rulePack.rulesStrings.136>-->
  <!--<TM_Book_Pools.rulePack.rulesStrings.137>TM_randNoun_Might->弓</TM_Book_Pools.rulePack.rulesStrings.137>-->
  <!--<TM_Book_Pools.rulePack.rulesStrings.138>TM_randNoun_Might->箭头</TM_Book_Pools.rulePack.rulesStrings.138>-->
  <!--<TM_Book_Pools.rulePack.rulesStrings.139>TM_randNoun_Might->挑战</TM_Book_Pools.rulePack.rulesStrings.139>-->
  <!--<TM_Book_Pools.rulePack.rulesStrings.140>TM_randNoun_Might->战斗</TM_Book_Pools.rulePack.rulesStrings.140>-->
  <!--<TM_Book_Pools.rulePack.rulesStrings.141>TM_randNoun_Might->战士</TM_Book_Pools.rulePack.rulesStrings.141>-->
  <!--<TM_Book_Pools.rulePack.rulesStrings.142>TM_randNoun_Might->角斗士</TM_Book_Pools.rulePack.rulesStrings.142>-->
  <!--<TM_Book_Pools.rulePack.rulesStrings.143>TM_randNoun_Might->雇佣兵</TM_Book_Pools.rulePack.rulesStrings.143>-->
  <!--<TM_Book_Pools.rulePack.rulesStrings.144>TM_randNoun_Might->骑士</TM_Book_Pools.rulePack.rulesStrings.144>-->
  <!--<TM_Book_Pools.rulePack.rulesStrings.145>TM_randNoun_Might->冠军</TM_Book_Pools.rulePack.rulesStrings.145>-->
  <!--<TM_Book_Pools.rulePack.rulesStrings.146>TM_randNoun_Might->士兵</TM_Book_Pools.rulePack.rulesStrings.146>-->
  <!--<TM_Book_Pools.rulePack.rulesStrings.147>TM_randNoun_Might->战斗机</TM_Book_Pools.rulePack.rulesStrings.147>-->
  <!--<TM_Book_Pools.rulePack.rulesStrings.148>TM_randNoun_Might->武士</TM_Book_Pools.rulePack.rulesStrings.148>-->
  <!--<TM_Book_Pools.rulePack.rulesStrings.149>TM_randNoun_Might->忍者</TM_Book_Pools.rulePack.rulesStrings.149>-->
  <!--<TM_Book_Pools.rulePack.rulesStrings.150>TM_randNoun_Might->刺客</TM_Book_Pools.rulePack.rulesStrings.150>-->
  <!--<TM_Book_Pools.rulePack.rulesStrings.151>TM_randNoun_Might->突击队</TM_Book_Pools.rulePack.rulesStrings.151>-->
  <!--<TM_Book_Pools.rulePack.rulesStrings.152>TM_randNoun_Might->狂战士</TM_Book_Pools.rulePack.rulesStrings.152>-->
  <!--<TM_Book_Pools.rulePack.rulesStrings.153>TM_randNoun_Might->圣骑士</TM_Book_Pools.rulePack.rulesStrings.153>-->
  <!--<TM_Book_Pools.rulePack.rulesStrings.154>subject_Might->战斗</TM_Book_Pools.rulePack.rulesStrings.154>-->
  <!--<TM_Book_Pools.rulePack.rulesStrings.155>subject_Might->战争</TM_Book_Pools.rulePack.rulesStrings.155>-->
  <!--<TM_Book_Pools.rulePack.rulesStrings.156>subject_Might->冲突</TM_Book_Pools.rulePack.rulesStrings.156>-->
  <!--<TM_Book_Pools.rulePack.rulesStrings.157>subject_Might->战斗</TM_Book_Pools.rulePack.rulesStrings.157>-->
  <!--<TM_Book_Pools.rulePack.rulesStrings.158>subject_Might->战斗</TM_Book_Pools.rulePack.rulesStrings.158>-->
  <!--<TM_Book_Pools.rulePack.rulesStrings.159>subject_Might->奋斗</TM_Book_Pools.rulePack.rulesStrings.159>-->
  <!--<TM_Book_Pools.rulePack.rulesStrings.160>subject_Might->征服</TM_Book_Pools.rulePack.rulesStrings.160>-->
  <!--<TM_Book_Pools.rulePack.rulesStrings.161>subject_Might->胜利</TM_Book_Pools.rulePack.rulesStrings.161>-->
  <!--<TM_Book_Pools.rulePack.rulesStrings.162>subject_Might->胜利</TM_Book_Pools.rulePack.rulesStrings.162>-->
  <!--<TM_Book_Pools.rulePack.rulesStrings.163>subject_Might->荣耀</TM_Book_Pools.rulePack.rulesStrings.163>-->
  <!--<TM_Book_Pools.rulePack.rulesStrings.164>subject_Might->价值</TM_Book_Pools.rulePack.rulesStrings.164>-->
  <!--<TM_Book_Pools.rulePack.rulesStrings.165>subject_Might->英雄主义</TM_Book_Pools.rulePack.rulesStrings.165>-->
  <!--<TM_Book_Pools.rulePack.rulesStrings.166>subject_Might->武器</TM_Book_Pools.rulePack.rulesStrings.166>-->
  <!--<TM_Book_Pools.rulePack.rulesStrings.167>subject_Might->战术</TM_Book_Pools.rulePack.rulesStrings.167>-->
  <!--<TM_Book_Pools.rulePack.rulesStrings.168>subject_Might->策略</TM_Book_Pools.rulePack.rulesStrings.168>-->
  <!--<TM_Book_Pools.rulePack.rulesStrings.169>subject_Might->战争</TM_Book_Pools.rulePack.rulesStrings.169>-->
  <!--<TM_Book_Pools.rulePack.rulesStrings.170>subject_Might->小冲突</TM_Book_Pools.rulePack.rulesStrings.170>-->
  <!--<TM_Book_Pools.rulePack.rulesStrings.171>subject_Might->攻击</TM_Book_Pools.rulePack.rulesStrings.171>-->
  <!--<TM_Book_Pools.rulePack.rulesStrings.172>subject_Might->防御</TM_Book_Pools.rulePack.rulesStrings.172>-->
  <!--<TM_Book_Pools.rulePack.rulesStrings.173>subject_Might->武术</TM_Book_Pools.rulePack.rulesStrings.173>-->
  <!--<TM_Book_Pools.rulePack.rulesStrings.174>subject_Might->决斗</TM_Book_Pools.rulePack.rulesStrings.174>-->
  <!--<TM_Book_Pools.rulePack.rulesStrings.175>subject_Might->竞技场战斗</TM_Book_Pools.rulePack.rulesStrings.175>-->
  <!--<TM_Book_Pools.rulePack.rulesStrings.176>subject_Might->军事</TM_Book_Pools.rulePack.rulesStrings.176>-->
  <!--<TM_Book_Pools.rulePack.rulesStrings.177>subject_Might->剑术</TM_Book_Pools.rulePack.rulesStrings.177>-->
  <!--<TM_Book_Pools.rulePack.rulesStrings.178>subject_Might->射箭</TM_Book_Pools.rulePack.rulesStrings.178>-->
  <!--<TM_Book_Pools.rulePack.rulesStrings.179>subject_Might->近战</TM_Book_Pools.rulePack.rulesStrings.179>-->
  <!--<TM_Book_Pools.rulePack.rulesStrings.180>subject_Might->近距离格斗</TM_Book_Pools.rulePack.rulesStrings.180>-->
  <!--<TM_Book_Pools.rulePack.rulesStrings.181>subject_Might->战士代码</TM_Book_Pools.rulePack.rulesStrings.181>-->
  <!--<TM_Book_Pools.rulePack.rulesStrings.182>subject_Might->命令</TM_Book_Pools.rulePack.rulesStrings.182>-->
  <!--<TM_Book_Pools.rulePack.rulesStrings.183>subject_Might->伏击</TM_Book_Pools.rulePack.rulesStrings.183>-->
  <!--<TM_Book_Pools.rulePack.rulesStrings.184>subject_Might->围攻</TM_Book_Pools.rulePack.rulesStrings.184>-->
  <!--<TM_Book_Pools.rulePack.rulesStrings.185>subject_Might->游击战</TM_Book_Pools.rulePack.rulesStrings.185>-->
  <!--<TM_Book_Pools.rulePack.rulesStrings.186>subject_Might->阵型</TM_Book_Pools.rulePack.rulesStrings.186>-->
  <!--<TM_Book_Pools.rulePack.rulesStrings.187>subject_Might->战场</TM_Book_Pools.rulePack.rulesStrings.187>-->
  <!--<TM_Book_Pools.rulePack.rulesStrings.188>subject_Might->武士精神</TM_Book_Pools.rulePack.rulesStrings.188>-->
  <!--<TM_Book_Pools.rulePack.rulesStrings.189>TM_randAdjective_Might->传奇的</TM_Book_Pools.rulePack.rulesStrings.189>-->
  <!--<TM_Book_Pools.rulePack.rulesStrings.190>TM_randAdjective_Might->英雄</TM_Book_Pools.rulePack.rulesStrings.190>-->
  <!--<TM_Book_Pools.rulePack.rulesStrings.191>TM_randAdjective_Might->无所畏惧</TM_Book_Pools.rulePack.rulesStrings.191>-->
  <!--<TM_Book_Pools.rulePack.rulesStrings.192>TM_randAdjective_Might->英勇</TM_Book_Pools.rulePack.rulesStrings.192>-->
  <!--<TM_Book_Pools.rulePack.rulesStrings.193>TM_randAdjective_Might->熟练</TM_Book_Pools.rulePack.rulesStrings.193>-->
  <!--<TM_Book_Pools.rulePack.rulesStrings.194>TM_randAdjective_Might->勇敢</TM_Book_Pools.rulePack.rulesStrings.194>-->
  <!--<TM_Book_Pools.rulePack.rulesStrings.195>TM_randAdjective_Might->激烈</TM_Book_Pools.rulePack.rulesStrings.195>-->
  <!--<TM_Book_Pools.rulePack.rulesStrings.196>TM_randAdjective_Might->强大</TM_Book_Pools.rulePack.rulesStrings.196>-->
  <!--<TM_Book_Pools.rulePack.rulesStrings.197>TM_randAdjective_Might->强大</TM_Book_Pools.rulePack.rulesStrings.197>-->
  <!--<TM_Book_Pools.rulePack.rulesStrings.198>TM_randAdjective_Might->迅速</TM_Book_Pools.rulePack.rulesStrings.198>-->
  <!--<TM_Book_Pools.rulePack.rulesStrings.199>TM_randAdjective_Might->敏捷</TM_Book_Pools.rulePack.rulesStrings.199>-->
  <!--<TM_Book_Pools.rulePack.rulesStrings.200>TM_randAdjective_Might->狡猾</TM_Book_Pools.rulePack.rulesStrings.200>-->
  <!--<TM_Book_Pools.rulePack.rulesStrings.201>TM_randAdjective_Might->顽强</TM_Book_Pools.rulePack.rulesStrings.201>-->
  <!--<TM_Book_Pools.rulePack.rulesStrings.202>TM_randAdjective_Might->弹性</TM_Book_Pools.rulePack.rulesStrings.202>-->
  <!--<TM_Book_Pools.rulePack.rulesStrings.203>TM_randAdjective_Might->坚定</TM_Book_Pools.rulePack.rulesStrings.203>-->
  <!--<TM_Book_Pools.rulePack.rulesStrings.204>TM_randAdjective_Might->大胆</TM_Book_Pools.rulePack.rulesStrings.204>-->
  <!--<TM_Book_Pools.rulePack.rulesStrings.205>TM_randAdjective_Might->坚韧</TM_Book_Pools.rulePack.rulesStrings.205>-->
  <!--<TM_Book_Pools.rulePack.rulesStrings.206>TM_randAdjective_Might->粗体</TM_Book_Pools.rulePack.rulesStrings.206>-->
  <!--<TM_Book_Pools.rulePack.rulesStrings.207>TM_randAdjective_Might->不屈</TM_Book_Pools.rulePack.rulesStrings.207>-->
  <!--<TM_Book_Pools.rulePack.rulesStrings.208>TM_randAdjective_Might->警惕</TM_Book_Pools.rulePack.rulesStrings.208>-->
  <!--<TM_Book_Pools.rulePack.rulesStrings.209>TM_randAdjective_Might->势不可挡</TM_Book_Pools.rulePack.rulesStrings.209>-->
  <!--<TM_Book_Pools.rulePack.rulesStrings.210>TM_randAdjective_Might->无情</TM_Book_Pools.rulePack.rulesStrings.210>-->
  <!--<TM_Book_Pools.rulePack.rulesStrings.211>TM_randAdjective_Might->无情</TM_Book_Pools.rulePack.rulesStrings.211>-->
  <!--<TM_Book_Pools.rulePack.rulesStrings.212>TM_randAdjective_Might->战术</TM_Book_Pools.rulePack.rulesStrings.212>-->
  <!--<TM_Book_Pools.rulePack.rulesStrings.213>TM_randAdjective_Might->战略</TM_Book_Pools.rulePack.rulesStrings.213>-->
  <!--<TM_Book_Pools.rulePack.rulesStrings.214>TM_randAdjective_Might->遵守纪律</TM_Book_Pools.rulePack.rulesStrings.214>-->
  <!--<TM_Book_Pools.rulePack.rulesStrings.215>TM_randAdjective_Might->尊敬</TM_Book_Pools.rulePack.rulesStrings.215>-->
  <!--<TM_Book_Pools.rulePack.rulesStrings.216>TM_randAdjective_Might->野蛮</TM_Book_Pools.rulePack.rulesStrings.216>-->
  <!--<TM_Book_Pools.rulePack.rulesStrings.217>TM_randAdjective_Might->致命</TM_Book_Pools.rulePack.rulesStrings.217>-->
  <!--<TM_Book_Pools.rulePack.rulesStrings.218>TM_randAdjective_Might->高贵</TM_Book_Pools.rulePack.rulesStrings.218>-->
  <!--<TM_Book_Pools.rulePack.rulesStrings.219>TM_randAdjective_Might->无情</TM_Book_Pools.rulePack.rulesStrings.219>-->
  <!--<TM_Book_Pools.rulePack.rulesStrings.220>TM_randTheme_Might->胜利</TM_Book_Pools.rulePack.rulesStrings.220>-->
  <!--<TM_Book_Pools.rulePack.rulesStrings.221>TM_randTheme_Might->荣誉</TM_Book_Pools.rulePack.rulesStrings.221>-->
  <!--<TM_Book_Pools.rulePack.rulesStrings.222>TM_randTheme_Might->价值</TM_Book_Pools.rulePack.rulesStrings.222>-->
  <!--<TM_Book_Pools.rulePack.rulesStrings.223>TM_randTheme_Might->勇气</TM_Book_Pools.rulePack.rulesStrings.223>-->
  <!--<TM_Book_Pools.rulePack.rulesStrings.224>TM_randTheme_Might->荣耀</TM_Book_Pools.rulePack.rulesStrings.224>-->
  <!--<TM_Book_Pools.rulePack.rulesStrings.225>TM_randTheme_Might->策略</TM_Book_Pools.rulePack.rulesStrings.225>-->
  <!--<TM_Book_Pools.rulePack.rulesStrings.226>TM_randTheme_Might->战术</TM_Book_Pools.rulePack.rulesStrings.226>-->
  <!--<TM_Book_Pools.rulePack.rulesStrings.227>TM_randTheme_Might->领导力</TM_Book_Pools.rulePack.rulesStrings.227>-->
  <!--<TM_Book_Pools.rulePack.rulesStrings.228>TM_randTheme_Might->兄弟会</TM_Book_Pools.rulePack.rulesStrings.228>-->
  <!--<TM_Book_Pools.rulePack.rulesStrings.229>TM_randTheme_Might->牺牲</TM_Book_Pools.rulePack.rulesStrings.229>-->
  <!--<TM_Book_Pools.rulePack.rulesStrings.230>TM_randTheme_Might->统一</TM_Book_Pools.rulePack.rulesStrings.230>-->
  <!--<TM_Book_Pools.rulePack.rulesStrings.231>TM_randTheme_Might->勇敢</TM_Book_Pools.rulePack.rulesStrings.231>-->
  <!--<TM_Book_Pools.rulePack.rulesStrings.232>TM_randTheme_Might->弹性</TM_Book_Pools.rulePack.rulesStrings.232>-->
  <!--<TM_Book_Pools.rulePack.rulesStrings.233>TM_randTheme_Might->职责</TM_Book_Pools.rulePack.rulesStrings.233>-->
  <!--<TM_Book_Pools.rulePack.rulesStrings.234>TM_randTheme_Might->正义</TM_Book_Pools.rulePack.rulesStrings.234>-->
  <!--<TM_Book_Pools.rulePack.rulesStrings.235>TM_randTheme_Might->尊重</TM_Book_Pools.rulePack.rulesStrings.235>-->
  <!--<TM_Book_Pools.rulePack.rulesStrings.236>TM_randTheme_Might->友情</TM_Book_Pools.rulePack.rulesStrings.236>-->
  <!--<TM_Book_Pools.rulePack.rulesStrings.237>TM_randTheme_Might->忠诚度</TM_Book_Pools.rulePack.rulesStrings.237>-->
  <!--<TM_Book_Pools.rulePack.rulesStrings.238>TM_randTheme_Might->训练</TM_Book_Pools.rulePack.rulesStrings.238>-->
  <!--<TM_Book_Pools.rulePack.rulesStrings.239>TM_randTheme_Might->准备</TM_Book_Pools.rulePack.rulesStrings.239>-->
  <!--<TM_Book_Pools.rulePack.rulesStrings.240>TM_randTheme_Might->战斗准备</TM_Book_Pools.rulePack.rulesStrings.240>-->
  <!--<TM_Book_Pools.rulePack.rulesStrings.241>TM_randTheme_Might->冲突解决</TM_Book_Pools.rulePack.rulesStrings.241>-->
  <!--<TM_Book_Pools.rulePack.rulesStrings.242>TM_randTheme_Might->耐力</TM_Book_Pools.rulePack.rulesStrings.242>-->
  <!--<TM_Book_Pools.rulePack.rulesStrings.243>TM_randTheme_Might->精通</TM_Book_Pools.rulePack.rulesStrings.243>-->
  <!--<TM_Book_Pools.rulePack.rulesStrings.244>TM_randTheme_Might->武士精神</TM_Book_Pools.rulePack.rulesStrings.244>-->
  <!--<TM_Book_Pools.rulePack.rulesStrings.245>TM_randTheme_Might->战场</TM_Book_Pools.rulePack.rulesStrings.245>-->
  <!--<TM_Book_Pools.rulePack.rulesStrings.246>TM_randTheme_Might->命令</TM_Book_Pools.rulePack.rulesStrings.246>-->
  <!--<TM_Book_Pools.rulePack.rulesStrings.247>TM_randTheme_Might->旧版</TM_Book_Pools.rulePack.rulesStrings.247>-->
  <!--<TM_Book_Pools.rulePack.rulesStrings.248>TM_randTheme_Might->战斗艺术</TM_Book_Pools.rulePack.rulesStrings.248>-->
  <!--<TM_Book_Pools.rulePack.rulesStrings.249>TM_randTheme_Might->武器精通</TM_Book_Pools.rulePack.rulesStrings.249>-->
  <!--<TM_Book_Pools.rulePack.rulesStrings.250>TM_randTheme_Might->生存</TM_Book_Pools.rulePack.rulesStrings.250>-->
  <!--<TM_Book_Pools.rulePack.rulesStrings.251>TM_randTheme_Might->训练方案</TM_Book_Pools.rulePack.rulesStrings.251>-->
  <!--<TM_Book_Pools.rulePack.rulesStrings.252>TM_randTheme_Might->武术纪律</TM_Book_Pools.rulePack.rulesStrings.252>-->
  <!--<TM_Book_Pools.rulePack.rulesStrings.253>TM_randTheme_Might->强度</TM_Book_Pools.rulePack.rulesStrings.253>-->
  <!--<TM_Book_Pools.rulePack.rulesStrings.254>TM_randTheme_Might->耐力</TM_Book_Pools.rulePack.rulesStrings.254>-->
  <!--<TM_Book_Pools.rulePack.rulesStrings.255>TM_randTheme_Might->毅力</TM_Book_Pools.rulePack.rulesStrings.255>-->
  <!--<TM_Book_Pools.rulePack.rulesStrings.256>TM_randTheme_Might->技能</TM_Book_Pools.rulePack.rulesStrings.256>-->
  <!--<TM_Book_Pools.rulePack.rulesStrings.257>TM_randTheme_Might->训练</TM_Book_Pools.rulePack.rulesStrings.257>-->


</LanguageData>